imgproxy_python/__init__.py
imgproxy_python/urls.py
imgproxy_python-0.0.2.dist-info/WHEEL
imgproxy_python-0.0.2.dist-info/METADATA
imgproxy_python-0.0.2.dist-info/RECORD
