Metadata-Version: 2.1
Name: imgproxy-python
Version: 0.0.2
Summary: A tiny library to simplify generation of imgproxy urls
Author: Vladislav_Gorelov
Author-email: rap-is-kal-again@yandex.ru
Requires-Python: >=3.6,<4.0
Classifier: Programming Language :: Python :: 3
Classifier: Programming Language :: Python :: 3.6
Classifier: Programming Language :: Python :: 3.7
Classifier: Programming Language :: Python :: 3.8
Classifier: Programming Language :: Python :: 3.9
